adbuiautolite/README.MD
adbuiautolite/__init__.py
adbuiautolite/requirements.txt
adbuiautolite/thirdparty.json
adbuiautolite-0.10.dist-info/LICENSE.rst
adbuiautolite-0.10.dist-info/METADATA
adbuiautolite-0.10.dist-info/WHEEL
adbuiautolite-0.10.dist-info/top_level.txt
adbuiautolite-0.10.dist-info/RECORD
