Metadata-Version: 2.1
Name: adbuiautolite
Version: 0.10
Summary: ADB - UiAutomator XML dump to pandas DataFrame
Home-page: https://github.com/hansalemaos/adbuiautolite
Author: Johannes Fischer
Author-email: aulasparticularesdealemaosp@gmail.com
License: MIT
Keywords: adb,android,pandas
Classifier: Development Status :: 4 - Beta
Classifier: Programming Language :: Python :: 3 :: Only
Classifier: Programming Language :: Python :: 3.10
Classifier: Topic :: Software Development :: Libraries :: Python Modules
Classifier: Topic :: Utilities
License-File: LICENSE.rst
Requires-Dist: a-pandas-ex-apply-ignore-exceptions
Requires-Dist: a-pandas-ex-less-memory-more-speed
Requires-Dist: pandas
Requires-Dist: pandasxmledit
Requires-Dist: regex
Requires-Dist: usefuladb
